model_navigator/__init__.py
model_navigator/__version__.py
model_navigator/exceptions.py
model_navigator/utilities.py
model_navigator/commands/__init__.py
model_navigator/commands/base.py
model_navigator/commands/delete_model.py
model_navigator/commands/execution_context.py
model_navigator/commands/infer_metadata.py
model_navigator/commands/load.py
model_navigator/commands/tensorrt_profile_builder.py
model_navigator/commands/convert/__init__.py
model_navigator/commands/convert/base.py
model_navigator/commands/convert/tf.py
model_navigator/commands/convert/torch.py
model_navigator/commands/convert/converters/__init__.py
model_navigator/commands/convert/converters/ep2torchtrt.py
model_navigator/commands/convert/converters/onnx2trt.py
model_navigator/commands/convert/converters/sm2tftrt.py
model_navigator/commands/convert/converters/ts2onnx.py
model_navigator/commands/convert/onnx/__init__.py
model_navigator/commands/convert/onnx/collect_onnx_input_metadata.py
model_navigator/commands/convert/onnx/onnx2trt.py
model_navigator/commands/copy/__init__.py
model_navigator/commands/copy/copy_model.py
model_navigator/commands/correctness/__init__.py
model_navigator/commands/correctness/correctness.py
model_navigator/commands/correctness/correctness_script.py
model_navigator/commands/data_dump/__init__.py
model_navigator/commands/data_dump/samples.py
model_navigator/commands/export/__init__.py
model_navigator/commands/export/tf.py
model_navigator/commands/export/torch.py
model_navigator/commands/export/exporters/__init__.py
model_navigator/commands/export/exporters/keras2savedmodel.py
model_navigator/commands/export/exporters/savedmodel2savedmodel.py
model_navigator/commands/export/exporters/torch2exportedprogram.py
model_navigator/commands/export/exporters/torch2onnx.py
model_navigator/commands/export/exporters/torch2quantized_onnx.py
model_navigator/commands/export/exporters/torch2torchscript.py
model_navigator/commands/find_max_batch_size/__init__.py
triton_model_navigator-0.14.0.dist-info/licenses/LICENSE
triton_model_navigator-0.14.0.dist-info/METADATA
triton_model_navigator-0.14.0.dist-info/WHEEL
triton_model_navigator-0.14.0.dist-info/top_level.txt
triton_model_navigator-0.14.0.dist-info/RECORD
