Metadata-Version: 2.4
Name: triton-model-navigator
Version: 0.14.0
Summary: Triton Model Navigator: An inference toolkit for optimizing and deploying machine learning models and pipelines on the Triton Inference Server and PyTriton.
License: Apache 2.0
Project-URL: Documentation, https://triton-inference-server.github.io/model_navigator
Project-URL: Source, https://github.com/triton-inference-server/model_navigator
Project-URL: Tracker, https://github.com/triton-inference-server/model_navigator/issues
Keywords: triton,inference,server,pytriton,inference,optimization,service,nvidia,tensorrt,onnx,tensorflow,pytorch,jax
Classifier: Development Status :: 3 - Alpha
Classifier: Intended Audience :: Science/Research
Classifier: Intended Audience :: Developers
Classifier: Topic :: Software Development
Classifier: Topic :: Scientific/Engineering
Classifier: Programming Language :: Python
Classifier: Programming Language :: Python :: 3
Classifier: Programming Language :: Python :: 3.9
Classifier: Programming Language :: Python :: 3.10
Classifier: Programming Language :: Python :: 3.11
Classifier: Programming Language :: Python :: 3.12
Classifier: Operating System :: POSIX
Classifier: Operating System :: Unix
Classifier: Operating System :: MacOS
Requires-Python: <4,>=3.9
License-File: LICENSE
Requires-Dist: dacite~=1.8
Requires-Dist: fire>=0.4.0
Requires-Dist: jsonlines>=3.1.0
Requires-Dist: loguru>=0.7.2
Requires-Dist: mpmath~=1.3
Requires-Dist: numpy<2
Requires-Dist: onnx~=1.16
Requires-Dist: onnx_graphsurgeon~=0.5
Requires-Dist: onnxruntime~=1.19; platform_machine == "aarch64" and python_version < "3.10"
Requires-Dist: onnxruntime-gpu~=1.19; platform_machine == "x86_64" and python_version < "3.10"
Requires-Dist: onnxruntime~=1.20; platform_machine == "aarch64" and python_version >= "3.10"
Requires-Dist: onnxruntime-gpu~=1.20; platform_machine == "x86_64" and python_version >= "3.10"
Requires-Dist: onnxscript
Requires-Dist: packaging~=24.1
Requires-Dist: polygraphy>=0.49.0
Requires-Dist: psutil>=5.7
Requires-Dist: py-cpuinfo>=8.0
Requires-Dist: pynvml~=11.5
Requires-Dist: python-slugify~=8.0
Requires-Dist: pyyaml~=6.0
Requires-Dist: tabulate>=0.8
Requires-Dist: tensorrt>=10.5.0
Requires-Dist: tritonclient[grpc]~=2.47
Requires-Dist: wrapt>=1.16
Requires-Dist: pyee>=11.1.0
Requires-Dist: rich>=13.7.1
Requires-Dist: nvidia-modelopt[onnx]>=0.27.0
Provides-Extra: torch
Requires-Dist: torch; extra == "torch"
Requires-Dist: torch_tensorrt>1; extra == "torch"
Requires-Dist: protobuf>=4; extra == "torch"
Provides-Extra: tensorflow
Requires-Dist: tensorflow; extra == "tensorflow"
Requires-Dist: tf2onnx>=1.9.3; extra == "tensorflow"
Requires-Dist: protobuf<3.21.0,>=3.18.3; extra == "tensorflow"
Provides-Extra: jax
Requires-Dist: jax[cuda12_pip]; extra == "jax"
Requires-Dist: tensorflow; extra == "jax"
Requires-Dist: tf2onnx>=1.9.3; extra == "jax"
Requires-Dist: protobuf<3.21.0,>=3.18.3; extra == "jax"
Provides-Extra: test
Requires-Dist: GitPython>=3.1.30; extra == "test"
Requires-Dist: pre-commit>=2.20.0; extra == "test"
Requires-Dist: pytest>=5.2; extra == "test"
Requires-Dist: pytest-mock>=3.8.2; extra == "test"
Requires-Dist: pytype!=2021.11.18,!=2022.2.17; extra == "test"
Requires-Dist: pytest-unordered~=0.5; extra == "test"
Requires-Dist: tenacity~=8.4.2; extra == "test"
Requires-Dist: tox>=3.23.1; extra == "test"
Requires-Dist: tqdm>=4.64.1; extra == "test"
Provides-Extra: doc
Requires-Dist: GitPython>=3.1.30; extra == "doc"
Requires-Dist: mike~=1.1.0; extra == "doc"
Requires-Dist: mkdocs-htmlproofer-plugin>=0.8.0; extra == "doc"
Requires-Dist: mkdocs-material>=8.5.6; extra == "doc"
Requires-Dist: mkdocstrings[python]<0.28.3,>=0.24.0; extra == "doc"
Requires-Dist: mkdocstrings-python>=1.7.0; extra == "doc"
Provides-Extra: dev
Requires-Dist: triton-model-navigator[test]; extra == "dev"
Requires-Dist: triton-model-navigator[doc]; extra == "dev"
Requires-Dist: build>=0.8; extra == "dev"
Requires-Dist: ipython>=7.16; extra == "dev"
Requires-Dist: pdbpp>=0.10; extra == "dev"
Requires-Dist: pip>=21.1; extra == "dev"
Requires-Dist: pre-commit>=2.20.0; extra == "dev"
Requires-Dist: psutil~=5.1; extra == "dev"
Requires-Dist: ruff>=0.3.0; extra == "dev"
Requires-Dist: twine>=4.0; extra == "dev"
Dynamic: license-file
